README.md
setup.cfg
setup.py
ExcelLibrary/ExcelLibrary.py
ExcelLibrary/__init__.py
ExcelLibrary/version.py
Tests/acceptance/ExcelRobotTest.txt
Tests/acceptance/ExcelRobotTest.xls
doc/ChangeLog.txt
doc/ExcelLibrary-KeywordDocumentation.html
robotframework_excellibrary_xwfintech.egg-info/PKG-INFO
robotframework_excellibrary_xwfintech.egg-info/SOURCES.txt
robotframework_excellibrary_xwfintech.egg-info/dependency_links.txt
robotframework_excellibrary_xwfintech.egg-info/requires.txt
robotframework_excellibrary_xwfintech.egg-info/top_level.txt